GenuineAI/__init__.py
GenuineAI/loss_functions.py
GenuineAI/metrics.py
tests/__init__.py
tests/test_aucloss.py
GenuineAI-0.1.0.dist-info/LICENSE
GenuineAI-0.1.0.dist-info/METADATA
GenuineAI-0.1.0.dist-info/WHEEL
GenuineAI-0.1.0.dist-info/top_level.txt
GenuineAI-0.1.0.dist-info/RECORD
