Metadata-Version: 2.1
Name: GenuineAI
Version: 0.1.0
Summary: Genuine AI functions used in iMICS Lab research projects
Home-page: UNKNOWN
Author: Ernest (Khashayar) Namdar
Author-email: ernest.namdar@utoronto.ca
License: UNKNOWN
Platform: UNKNOWN
Classifier: Programming Language :: Python :: 3
Classifier: License :: OSI Approved :: MIT License
Classifier: Operating System :: OS Independent
License-File: LICENSE
